mocap_calibration/__init__.py
mocap_calibration/axengine_1765477996_3220093488.py
mocap_calibration/calib_eval/__init__.py
mocap_calibration/calib_eval/calib_eval_with_manual_kpts.py
mocap_calibration/calibration/__init__.py
mocap_calibration/calibration/aruco/__init__.py
mocap_calibration/calibration/aruco/aruco_calib.py
mocap_calibration/calibration/aruco/main_calib_aruco.py
mocap_calibration/calibration/aruco/ppl_calib_aruco.py
mocap_calibration/calibration/aruco/quality.py
mocap_calibration/calibration/calib_obj/__init__.py
mocap_calibration/calibration/calib_obj/calibration_obj.py
mocap_calibration/calibration/calib_obj/detect_calib_obj.py
mocap_calibration/calibration/calib_obj/pair_calib_obj.py
mocap_calibration/calibration/calib_obj/tests/__init__.py
mocap_calibration/calibration/calib_obj/tests/aruco_calib.py
mocap_calibration/calibration/calib_obj/tests/calib_football_court.py
mocap_calibration/calibration/calib_obj/tests/calibration_obj_test.py
mocap_calibration/calibration/calib_obj/tests/check_aruco_with_gt.py
mocap_calibration/calibration/calib_obj/tests/detect_lines.py
mocap_calibration/calibration/calib_obj/tests/manual_calibration.py
mocap_calibration/calibration/calib_obj/tests/solvePnP.py
mocap_calibration/calibration/calib_obj/tests/vis_aruco_calib.py
mocap_calibration/calibration/calib_obj/tests/vis_manual_calib.py
mocap_calibration/calibration/calib_obj/utils.py
mocap_calibration/calibration/cam_intrinsics/__init__.py
mocap_calibration/calibration/cam_intrinsics/calc_intrinsics.py
mocap_calibration/calibration/cam_intrinsics/calc_intrinsics_app.py
mocap_calibration/calibration/cam_intrinsics/intrinsic_calib.sh
mocap_calibration/calibration/cam_intrinsics/set_webcam_settings.sh
mocap_calibration/calibration/cam_intrinsics/undistort_app.py
mocap_calibration/calibration/cam_intrinsics/undistort_img.py
mocap_calibration/calibration/cam_intrinsics/undistort_video.py
mocap_calibration/calibration/cam_intrinsics/undistort_videos_from_json.py
mocap_calibration-2.10.6.dist-info/METADATA
mocap_calibration-2.10.6.dist-info/WHEEL
mocap_calibration-2.10.6.dist-info/RECORD
