Metadata-Version: 2.1
Name: mocap-calibration
Version: 2.10.6
Summary: 
Keywords: MotionOps,Moveai
Author: move.ai
Author-email: info@move.ai
Requires-Python: >=3.10,<4.0
Classifier: Programming Language :: Python :: 3
Classifier: Programming Language :: Python :: 3.10
Classifier: Programming Language :: Python :: 3.11
Classifier: Programming Language :: Python :: 3.12
Requires-Dist: fpdf (>=1.7.2,<2.0.0)
Requires-Dist: mocap-base (>=2.0.1,<3.0.0)
Requires-Dist: mocap_settings (>=1.6.9,<2.0.0)
Requires-Dist: moviepy (>=1.0.3,<2.0.0)
Requires-Dist: networkx (>=3.4.2,<4.0.0)
Requires-Dist: opencv-python (>=4.10,<5.0)
Requires-Dist: pyexiftool (==0.4.13)
Requires-Dist: scikit-learn (>=1.3.1,<2.0.0)
